{
  "lastUpdated": "2026-07-10T15:40+00:00",
  "sourceStrength": "High",
  "freshness": "Live mirror",
  "whatChanged": "USGS and NWS published data were mirrored into local JSON by GitHub Actions.",
  "sourceLinks": [
    {
      "label": "USGS",
      "url": "https://earthquake.usgs.gov/earthquakes/feed/"
    },
    {
      "label": "NWS Alerts API",
      "url": "https://www.weather.gov/documentation/services-web-api"
    }
  ],
  "notes": [
    "This tile is event-card driven rather than using a synthetic single score."
  ],
  "events": [
    {
      "type": "Earthquake",
      "region": "28 km NNE of Aleneva, Alaska",
      "severity": "Low"
    },
    {
      "type": "Earthquake",
      "region": "28 km WSW of Coyanosa, Texas",
      "severity": "Low"
    },
    {
      "type": "Earthquake",
      "region": "64 km WNW of Toyah, Texas",
      "severity": "Low"
    },
    {
      "type": "Earthquake",
      "region": "6 km SSE of Big Bear Lake, CA",
      "severity": "Low"
    },
    {
      "type": "Earthquake",
      "region": "4 km NNW of The Geysers, CA",
      "severity": "Low"
    },
    {
      "type": "Earthquake",
      "region": "43 km NW of Tatitlek, Alaska",
      "severity": "Low"
    },
    {
      "type": "Earthquake",
      "region": "7 km WSW of Chickaloon, Alaska",
      "severity": "Low"
    },
    {
      "type": "Earthquake",
      "region": "13 km NNW of Cantwell, Alaska",
      "severity": "Low"
    },
    {
      "type": "Lake Wind Advisory issued July 10 at 6:31AM PDT until July 10 at 11:00PM PDT by NWS Hanford CA",
      "region": "West Side Mountains north of 198",
      "severity": "Moderate"
    },
    {
      "type": "Lake Wind Advisory issued July 10 at 6:31AM PDT until July 10 at 11:00PM PDT by NWS Hanford CA",
      "region": "Kern River Valley",
      "severity": "Moderate"
    },
    {
      "type": "Red Flag Warning issued July 10 at 3:29AM PDT until July 12 at 9:00PM PDT by NWS Medford OR",
      "region": "Modoc County Except for the Surprise Valley; Klamath Basin and the Fremont-Winema National Forest",
      "severity": "Severe"
    },
    {
      "type": "Heat Advisory issued July 10 at 2:30AM PDT until July 10 at 8:00PM PDT by NWS San Diego CA",
      "region": "San Bernardino County Mountains",
      "severity": "Moderate"
    }
  ],
  "sourceType": "automated",
  "refreshStatus": "success",
  "lastAttemptedAt": "2026-07-10T15:40+00:00",
  "lastSuccessfulAt": "2026-07-10T15:40+00:00",
  "sourceLimitations": [
    "Mirrors public USGS and NWS feeds; it is not a full supply-chain disruption model."
  ]
}
