{
  "lastUpdated": "2026-05-19T16:32+00:00",
  "sourceStrength": "High",
  "freshness": "Live mirror",
  "whatChanged": "USGS and NWS published data were mirrored into local JSON by GitHub Actions.",
  "sourceLinks": [
    {
      "label": "USGS",
      "url": "https://earthquake.usgs.gov/earthquakes/feed/"
    },
    {
      "label": "NWS Alerts API",
      "url": "https://www.weather.gov/documentation/services-web-api"
    }
  ],
  "notes": [
    "This tile is event-card driven rather than using a synthetic single score."
  ],
  "events": [
    {
      "type": "Earthquake",
      "region": "6 km W of Calimesa, CA",
      "severity": "Low"
    },
    {
      "type": "Earthquake",
      "region": "16 km ESE of Barstow, Texas",
      "severity": "Low"
    },
    {
      "type": "Earthquake",
      "region": "44 km WSW of Healy, Alaska",
      "severity": "Low"
    },
    {
      "type": "Earthquake",
      "region": "8 km WSW of Larsen Bay, Alaska",
      "severity": "Low"
    },
    {
      "type": "Earthquake",
      "region": "8 km SE of Pearsall, Texas",
      "severity": "Low"
    },
    {
      "type": "Earthquake",
      "region": "2 km NW of The Geysers, CA",
      "severity": "Low"
    },
    {
      "type": "Earthquake",
      "region": "42 km NW of Toyah, Texas",
      "severity": "Low"
    },
    {
      "type": "Earthquake",
      "region": "22 km W of Petrolia, CA",
      "severity": "Low"
    },
    {
      "type": "Air Quality Alert issued May 18 at 7:41PM PDT by NWS Los Angeles/Oxnard CA",
      "region": "Santa Clarita Valley; Malibu Coast; Los Angeles County Beaches; Palos Verdes Hills; Los Angeles County Inland Coast including Downtown Los Angeles; Western Santa Monica Mountains Recreational Area; Eastern Santa Monica Mountains Recreational Area; Calabasas and Agoura Hills; Western San Fernando Valley; Eastern San Fernando Valley; Santa Susana Mountains; Interstate 5 Corridor; Western San Gabriel Mountains and Highway 14 Corridor; Eastern San Gabriel Mountains; Los Angeles County San Gabriel Valley",
      "severity": "Unknown"
    },
    {
      "type": "Air Quality Alert issued May 18 at 7:40PM PDT by NWS San Diego CA",
      "region": "Santa Ana Mountains and Foothills; Orange County Coastal; Orange County Inland",
      "severity": "Unknown"
    },
    {
      "type": "Air Quality Alert issued May 18 at 7:18PM PDT by NWS Los Angeles/Oxnard CA",
      "region": "Eastern San Fernando Valley; Eastern San Gabriel Mountains; Eastern Santa Monica Mountains Recreational Area; Interstate 5 Corridor; Los Angeles County Beaches; Los Angeles County Inland Coast including Downtown Los Angeles; Los Angeles County San Gabriel Valley; Palos Verdes Hills; Santa Clarita Valley; Santa Susana Mountains; Western San Fernando Valley; Western San Gabriel Mountains and Highway 14 Corridor; Western Santa Monica Mountains Recreational Area",
      "severity": "Unknown"
    }
  ]
}